slack_xblock/__init__.py
slack_xblock/settings.py
slack_xblock/slack_xblock.py
slack_xblock/static/README.txt
slack_xblock/static/css/slack_xblock.css
slack_xblock/static/html/slack_xblock.html
slack_xblock/static/html/slack_xblock_edit.html
slack_xblock/static/js/src/slack_xblock.js
slack_xblock/static/js/src/slack_xblock_edit.js
slack_xblock/templates/studio_edit.html
slack_xblock/translations/README.txt
slack_xblock-0.1.0.dist-info/METADATA
slack_xblock-0.1.0.dist-info/WHEEL
slack_xblock-0.1.0.dist-info/entry_points.txt
slack_xblock-0.1.0.dist-info/licenses/LICENSE
slack_xblock-0.1.0.dist-info/RECORD
