Metadata-Version: 2.4
Name: slack-xblock
Version: 0.1.0
Summary: A simple XBlock to add a Slack channel link to Open edX courses.
License-Expression: Apache-2.0
License-File: LICENSE
Keywords: xblock,openedx,slack
Author: Zawadi .W
Requires-Python: >=3.9
Classifier: Programming Language :: Python :: 3
Classifier: Programming Language :: Python :: 3.9
Classifier: Programming Language :: Python :: 3.10
Classifier: Programming Language :: Python :: 3.11
Classifier: Programming Language :: Python :: 3.12
Classifier: Programming Language :: Python :: 3.13
Classifier: Programming Language :: Python :: 3.14
Requires-Dist: XBlock
Requires-Dist: django
Requires-Dist: python-decouple
Requires-Dist: requests
Requires-Dist: xblock-utils
Project-URL: Bug Tracker, https://github.com/3N61N33R/slack-xblock/issues
Project-URL: Homepage, https://github.com/3N61N33R/slack-xblock
Project-URL: Repository, https://github.com/3N61N33R/slack-xblock
